{"quote": {"result": [{"language": "en-US", "region": "US", "quoteType": "EQUITY", "typeDisp": "Equity", "quoteSourceName": "Delayed Quote", "triggerable": false, "customPriceAlertConfidence": "LOW", "currency": "CNY", "exchange": "SHZ", "shortName": "CHANGSHU TIANYIN E", "longName": "Changshu Tianyin Electromechanical Co.,Ltd", "messageBoardId": "finmb_58145214", "exchangeTimezoneName": "Asia/Shanghai", "exchangeTimezoneShortName": "CST", "gmtOffSetMilliseconds": 28800000, "market": "cn_market", "esgPopulated": false, "regularMarketChangePercent": -1.9874532, "regularMarketPrice": 9.37, "marketState": "POSTPOST", "fiftyTwoWeekHighChangePercent": -0.17807016, "fiftyTwoWeekLow": 7.68, "fiftyTwoWeekHigh": 11.4, "earningsTimestamp": 1619521140, "earningsTimestampStart": 1619521140, "earningsTimestampEnd": 1619521140, "trailingAnnualDividendRate": 0.0, "trailingPE": 156.16667, "trailingAnnualDividendYield": 0.0, "epsTrailingTwelveMonths": 0.06, "epsForward": 0.87, "sharesOutstanding": 425035008, "bookValue": 3.546, "fiftyDayAverage": 9.959, "fiftyDayAverageChange": -0.58899975, "fiftyDayAverageChangePercent": -0.059142463, "twoHundredDayAverage": 9.25175, "twoHundredDayAverageChange": 0.11824989, "twoHundredDayAverageChangePercent": 0.012781355, "marketCap": 3982577920, "forwardPE": 10.770115, "priceToBook": 2.6424139, "sourceInterval": 15, "exchangeDataDelayedBy": 15, "tradeable": false, "cryptoTradeable": false, "priceHint": 2, "regularMarketChange": -0.19000053, "regularMarketTime": 1683875074, "regularMarketDayHigh": 9.64, "regularMarketDayRange": "9.37 - 9.64", "regularMarketDayLow": 9.37, "regularMarketVolume": 5887028, "regularMarketPreviousClose": 9.56, "bid": 9.39, "ask": 9.4, "bidSize": 0, "askSize": 0, "fullExchangeName": "Shenzhen", "financialCurrency": "CNY", "regularMarketOpen": 9.61, "averageDailyVolume3Month": 16352630, "averageDailyVolume10Day": 10788444, "fiftyTwoWeekLowChange": 1.69, "fiftyTwoWeekLowChangePercent": 0.2200521, "fiftyTwoWeekRange": "7.68 - 11.4", "fiftyTwoWeekHighChange": -2.0299997, "firstTradeDateMilliseconds": 1343266200000, "symbol": "300342.SZ"}], "error": null}, "summary": {"result": [{"assetProfile": {"address1": "No. 8, Yingbin Road", "address2": "Bixi New District", "city": "Changshu", "zip": "215513", "country": "China", "phone": "86 51 2526 91551", "fax": "86 51 2526 91888", "website": "https://www.tyjd.cc", "industry": "Electrical Equipment & Parts", "industryDisp": "Electrical Equipment & Parts", "sector": "Industrials", "longBusinessSummary": "Changshu Tianyin Electromechanical Co.,Ltd engages in the research and development, production, and sale of refrigerator compressor parts in China. It offers thermal overload protectors; PTC starter relays; junction boxes for various refrigeration appliances; current start relays; starter protectors; plastic suction mufflers for various refrigerator compressors; plastic compression spring bearings; and refrigerator compressor inverter controllers. The company was founded in 2002 and is based in Changshu, China.", "fullTimeEmployees": 990, "companyOfficers": [{"maxAge": 1, "name": "Mr. Yunwen  Zhao", "age": 67, "title": "GM & Non-Independent Director", "yearBorn": 1955, "exercisedValue": {"raw": 0, "fmt": null, "longFmt": "0"}, "unexercisedValue": {"raw": 0, "fmt": null, "longFmt": "0"}}, {"maxAge": 1, "name": "Ms. Fang  Lin", "age": 30, "title": "Financial Director & Non-Independent Director", "yearBorn": 1992, "exercisedValue": {"raw": 0, "fmt": null, "longFmt": "0"}, "unexercisedValue": {"raw": 0, "fmt": null, "longFmt": "0"}}, {"maxAge": 1, "name": "Ms. Lingli  Ge", "age": 36, "title": "Deputy Gen. Mang.", "yearBorn": 1986, "exercisedValue": {"raw": 0, "fmt": null, "longFmt": "0"}, "unexercisedValue": {"raw": 0, "fmt": null, "longFmt": "0"}}, {"maxAge": 1, "name": "Mr. Jian  Li", "age": 48, "title": "Deputy Gen. Mang.", "yearBorn": 1974, "exercisedValue": {"raw": 0, "fmt": null, "longFmt": "0"}, "unexercisedValue": {"raw": 0, "fmt": null, "longFmt": "0"}}, {"maxAge": 1, "name": "Mr. Weiguo  Su", "age": 48, "title": "Deputy Gen. Mang.", "yearBorn": 1974, "exercisedValue": {"raw": 0, "fmt": null, "longFmt": "0"}, "unexercisedValue": {"raw": 0, "fmt": null, "longFmt": "0"}}, {"maxAge": 1, "name": "Mr. Xiao Dong  Zhao", "age": 42, "title": "Deputy GM & Director", "yearBorn": 1980, "exercisedValue": {"raw": 0, "fmt": null, "longFmt": "0"}, "unexercisedValue": {"raw": 0, "fmt": null, "longFmt": "0"}}], "maxAge": 86400}}], "error": null}}