{"quote": {"result": [{"language": "en-US", "region": "US", "quoteType": "EQUITY", "typeDisp": "Equity", "quoteSourceName": "Delayed Quote", "triggerable": false, "customPriceAlertConfidence": "LOW", "currency": "EUR", "regularMarketChangePercent": 0.974793, "regularMarketPrice": 15.02, "trailingAnnualDividendRate": 0.0, "trailingAnnualDividendYield": 0.0, "epsTrailingTwelveMonths": -0.03, "sharesOutstanding": 231944000, "bookValue": 19.575, "fiftyDayAverage": 13.7194, "fiftyDayAverageChange": 1.3006, "fiftyDayAverageChangePercent": 0.09480006, "twoHundredDayAverage": 11.97464, "twoHundredDayAverageChange": 3.0453606, "twoHundredDayAverageChangePercent": 0.2543175, "marketCap": 3869122048, "priceToBook": 0.76730525, "sourceInterval": 15, "exchangeDataDelayedBy": 15, "tradeable": false, "cryptoTradeable": false, "firstTradeDateMilliseconds": 1531980000000, "priceHint": 2, "marketState": "REGULAR", "exchange": "FRA", "shortName": "AMBU A/S NAM. B DK -,50", "longName": "Ambu A/S", "messageBoardId": "finmb_878918", "exchangeTimezoneName": "Europe/Berlin", "exchangeTimezoneShortName": "CEST", "gmtOffSetMilliseconds": 7200000, "market": "dr_market", "esgPopulated": false, "regularMarketChange": 0.14500046, "regularMarketTime": 1683892037, "regularMarketDayHigh": 15.02, "regularMarketDayRange": "14.69 - 15.02", "regularMarketDayLow": 14.69, "regularMarketVolume": 300, "regularMarketPreviousClose": 14.875, "bid": 15.0, "ask": 15.305, "bidSize": 0, "askSize": 0, "fullExchangeName": "Frankfurt", "financialCurrency": "DKK", "regularMarketOpen": 14.69, "averageDailyVolume3Month": 45, "averageDailyVolume10Day": 80, "fiftyTwoWeekLowChange": 6.7940006, "fiftyTwoWeekLowChangePercent": 0.8259179, "fiftyTwoWeekRange": "8.226 - 15.94", "fiftyTwoWeekHighChange": -0.9199991, "fiftyTwoWeekHighChangePercent": -0.057716385, "fiftyTwoWeekLow": 8.226, "fiftyTwoWeekHigh": 15.94, "symbol": "547A.F"}], "error": null}, "summary": {"result": [{"assetProfile": {"address1": "Baltorpbakken 13", "city": "Ballerup", "zip": "2750", "country": "Denmark", "phone": "45 72 25 20 00", "website": "https://www.ambu.com", "industry": "Medical Devices", "industryDisp": "Medical Devices", "sector": "Healthcare", "longBusinessSummary": "Ambu A/S develops, produces, and sells medical devices to hospitals, clinics, and rescue services worldwide. It provides healthcare solutions in the fields of visualization, anesthesia, and patient monitoring and diagnostics. The company offers endoscopy products, such as bronchoscopes and monitors; and neurology products, including EEG and EMG electrodes, EMG guided injections, and intraoperative monitoring products. It also provides cardiology products consisting of ECG electrodes; and airway management and anaesthesia products, such as bronchoscopes, video laryngoscopes, double and single lumen tubes, endobronchial blockers, laryngeal and face masks, breathing bags, and resuscitators. In addition, the company offers extrication collars, CPR breathing barriers, video laryngoscopes, and training manikins. Ambu A/S was founded in 1937 and is headquartered in Ballerup, Denmark.", "fullTimeEmployees": 4500, "companyOfficers": [{"maxAge": 1, "name": "Ms. Britt Meelby Jensen", "age": 49, "title": "Chief Exec. Officer", "yearBorn": 1973, "fiscalYear": 2022, "totalPay": {"raw": 637358, "fmt": "637.36k", "longFmt": "637,358"}, "exercisedValue": {"raw": 0, "fmt": null, "longFmt": "0"}, "unexercisedValue": {"raw": 0, "fmt": null, "longFmt": "0"}}, {"maxAge": 1, "name": "Mr. Thomas Frederik Schmidt", "age": 51, "title": "Exec. VP & CFO", "yearBorn": 1971, "fiscalYear": 2022, "totalPay": {"raw": 596566, "fmt": "596.57k", "longFmt": "596,566"}, "exercisedValue": {"raw": 0, "fmt": null, "longFmt": "0"}, "unexercisedValue": {"raw": 0, "fmt": null, "longFmt": "0"}}, {"maxAge": 1, "name": "Mr. Thomas Lykke Henriksen", "age": 49, "title": "Head of HR Systems", "yearBorn": 1973, "fiscalYear": 2022, "totalPay": {"raw": 10603, "fmt": "10.6k", "longFmt": "10,603"}, "exercisedValue": {"raw": 0, "fmt": null, "longFmt": "0"}, "unexercisedValue": {"raw": 0, "fmt": null, "longFmt": "0"}}, {"maxAge": 1, "name": "Holger  Hesse", "title": "Founder", "exercisedValue": {"raw": 0, "fmt": null, "longFmt": "0"}, "unexercisedValue": {"raw": 0, "fmt": null, "longFmt": "0"}}, {"maxAge": 1, "name": "Mr. Henrik  Ankj\u00e6r", "title": "Exec. VP of Global Operations", "exercisedValue": {"raw": 0, "fmt": null, "longFmt": "0"}, "unexercisedValue": {"raw": 0, "fmt": null, "longFmt": "0"}}, {"maxAge": 1, "name": "Mr. Nicolai  Thomsen", "title": "Director of Investor Relations & Strategic Financial Planning", "exercisedValue": {"raw": 0, "fmt": null, "longFmt": "0"}, "unexercisedValue": {"raw": 0, "fmt": null, "longFmt": "0"}}, {"maxAge": 1, "name": "Mikkel Trier Wagner", "title": "Director of Corp. Communications", "exercisedValue": {"raw": 0, "fmt": null, "longFmt": "0"}, "unexercisedValue": {"raw": 0, "fmt": null, "longFmt": "0"}}, {"maxAge": 1, "name": "Mr. Bassel  Rifai", "title": "Exec. VP, Chief Marketing Officer & Pres APAC", "exercisedValue": {"raw": 0, "fmt": null, "longFmt": "0"}, "unexercisedValue": {"raw": 0, "fmt": null, "longFmt": "0"}}, {"maxAge": 1, "name": "Mr. M\u00e5ns  Barsne", "title": "Exec. VP of Global Innovation & Chief Innovation Officer", "exercisedValue": {"raw": 0, "fmt": null, "longFmt": "0"}, "unexercisedValue": {"raw": 0, "fmt": null, "longFmt": "0"}}, {"maxAge": 1, "name": "Mr. Steven R. Block", "age": 59, "title": "CEO & Pres of USA", "yearBorn": 1963, "exercisedValue": {"raw": 0, "fmt": null, "longFmt": "0"}, "unexercisedValue": {"raw": 0, "fmt": null, "longFmt": "0"}}], "auditRisk": 2, "boardRisk": 1, "compensationRisk": 5, "shareHolderRightsRisk": 10, "overallRisk": 2, "governanceEpochDate": 1682899200, "compensationAsOfEpochDate": 1672444800, "maxAge": 86400}}], "error": null}}