{"quote": {"result": [{"language": "en-US", "region": "US", "quoteType": "EQUITY", "typeDisp": "Equity", "triggerable": false, "customPriceAlertConfidence": "LOW", "currency": "HKD", "marketState": "CLOSED", "exchangeTimezoneShortName": "HKT", "gmtOffSetMilliseconds": 28800000, "esgPopulated": false, "regularMarketChangePercent": -5.0279346, "regularMarketPrice": 0.17, "exchange": "HKG", "shortName": "EASY REPAY FIN", "longName": "Easy Repay Finance & Investment Limited", "messageBoardId": "finmb_7653108", "exchangeTimezoneName": "Asia/Hong_Kong", "market": "hk_market", "regularMarketTime": 1683878223, "regularMarketDayHigh": 0.175, "regularMarketDayRange": "0.165 - 0.175", "regularMarketDayLow": 0.165, "regularMarketVolume": 220000, "regularMarketPreviousClose": 0.179, "bid": 0.17, "ask": 0.174, "bidSize": 0, "askSize": 0, "fullExchangeName": "HKSE", "financialCurrency": "HKD", "regularMarketOpen": 0.175, "averageDailyVolume3Month": 1049233, "averageDailyVolume10Day": 510750, "fiftyTwoWeekLowChange": 0.061000004, "fiftyTwoWeekLowChangePercent": 0.5596331, "fiftyTwoWeekRange": "0.109 - 0.33", "fiftyTwoWeekHighChange": -0.16000001, "fiftyTwoWeekHighChangePercent": -0.4848485, "fiftyTwoWeekLow": 0.109, "fiftyTwoWeekHigh": 0.33, "earningsTimestamp": 1676284322, "earningsTimestampStart": 1676284322, "earningsTimestampEnd": 1676284322, "trailingAnnualDividendRate": 0.0, "trailingAnnualDividendYield": 0.0, "epsTrailingTwelveMonths": -0.22, "sharesOutstanding": 432644000, "bookValue": 0.576, "fiftyDayAverage": 0.1715, "fiftyDayAverageChange": -0.0014999956, "fiftyDayAverageChangePercent": -0.00874633, "twoHundredDayAverage": 0.17319146, "twoHundredDayAverageChange": -0.0031914562, "twoHundredDayAverageChangePercent": -0.018427331, "marketCap": 77443328, "priceToBook": 0.2951389, "sourceInterval": 15, "exchangeDataDelayedBy": 15, "tradeable": false, "cryptoTradeable": false, "firstTradeDateMilliseconds": 1127957400000, "priceHint": 3, "regularMarketChange": -0.009000003, "symbol": "8079.HK"}], "error": null}, "summary": {"result": [{"assetProfile": {"address1": "Unit 02", "address2": "11th Floor Eastmark 21 Sheung Yuet Road", "city": "Kowloon Bay", "country": "Hong Kong", "phone": "852 2898 0567", "website": "https://www.ecrepay.com", "industry": "Grocery Stores", "industryDisp": "Grocery Stores", "sector": "Consumer Defensive", "longBusinessSummary": "Easy Repay Finance & Investment Limited engages in the retail and wholesale of grocery products in Hong Kong. The company sells grocery products, such as frozen and processed food through retail and online channels. It is also involved in money lending, and financial instruments and quoted shares investment businesses, as well as property investment business. In addition, the company offers beauty and clinical services; retails beauty products; and trades in cash coupons. The company was formerly known as Unlimited Creativity Holdings Limited and changed its name to Easy Repay Finance & Investment Limited in April 2015. Easy Repay Finance & Investment Limited is headquartered in Cheung Sha Wan, Hong Kong.", "fullTimeEmployees": 90, "companyOfficers": [{"maxAge": 1, "name": "Ms. Yeuk Hung  Siu", "age": 57, "title": "CEO, Compliance Officer & Exec. Director", "yearBorn": 1965, "fiscalYear": 2022, "totalPay": {"raw": 821000, "fmt": "821k", "longFmt": "821,000"}, "exercisedValue": {"raw": 0, "fmt": null, "longFmt": "0"}, "unexercisedValue": {"raw": 0, "fmt": null, "longFmt": "0"}}, {"maxAge": 1, "name": "Mr. Ka Kei  Law", "age": 46, "title": "Exec. Director", "yearBorn": 1976, "fiscalYear": 2022, "totalPay": {"raw": 700000, "fmt": "700k", "longFmt": "700,000"}, "exercisedValue": {"raw": 0, "fmt": null, "longFmt": "0"}, "unexercisedValue": {"raw": 0, "fmt": null, "longFmt": "0"}}, {"maxAge": 1, "name": "Mr. Yan Tak  Chan", "age": 53, "title": "Exec. Chairman", "yearBorn": 1969, "exercisedValue": {"raw": 0, "fmt": null, "longFmt": "0"}, "unexercisedValue": {"raw": 0, "fmt": null, "longFmt": "0"}}, {"maxAge": 1, "name": "Mr. Ming Shing  Lim", "age": 61, "title": "Exec. Director", "yearBorn": 1961, "exercisedValue": {"raw": 0, "fmt": null, "longFmt": "0"}, "unexercisedValue": {"raw": 0, "fmt": null, "longFmt": "0"}}, {"maxAge": 1, "name": "Mr. Chi  To C.P.A., CPA, FCCA", "age": 57, "title": "Company Sec.", "yearBorn": 1965, "exercisedValue": {"raw": 0, "fmt": null, "longFmt": "0"}, "unexercisedValue": {"raw": 0, "fmt": null, "longFmt": "0"}}], "compensationAsOfEpochDate": 1672444800, "maxAge": 86400}}], "error": null}}