{"quote": {"result": [{"language": "en-US", "region": "US", "quoteType": "EQUITY", "typeDisp": "Equity", "quoteSourceName": "Delayed Quote", "triggerable": false, "customPriceAlertConfidence": "LOW", "currency": "EUR", "marketState": "REGULAR", "regularMarketPrice": 8.35, "exchange": "FRA", "shortName": "LADDER CAP.CORP.A DL-,001", "longName": "Ladder Capital Corp", "messageBoardId": "finmb_216667093", "exchangeTimezoneName": "Europe/Berlin", "exchangeTimezoneShortName": "CEST", "gmtOffSetMilliseconds": 7200000, "market": "dr_market", "esgPopulated": false, "regularMarketChangePercent": 0.6024119, "firstTradeDateMilliseconds": 1392188400000, "priceHint": 2, "regularMarketChange": 0.05000019, "regularMarketTime": 1683892036, "regularMarketDayHigh": 8.4, "regularMarketDayRange": "8.35 - 8.4", "regularMarketDayLow": 8.35, "regularMarketVolume": 100, "regularMarketPreviousClose": 8.3, "bid": 8.35, "ask": 8.5, "bidSize": 410, "askSize": 400, "fullExchangeName": "Frankfurt", "financialCurrency": "USD", "regularMarketOpen": 8.4, "averageDailyVolume3Month": 6, "averageDailyVolume10Day": 10, "fiftyTwoWeekLowChange": 0.40000057, "fiftyTwoWeekLowChangePercent": 0.05031454, "fiftyTwoWeekRange": "7.95 - 11.5", "fiftyTwoWeekHighChange": -3.1499996, "fiftyTwoWeekHighChangePercent": -0.273913, "fiftyTwoWeekLow": 7.95, "fiftyTwoWeekHigh": 11.5, "earningsTimestamp": 1682629200, "earningsTimestampStart": 1690369140, "earningsTimestampEnd": 1690804800, "trailingAnnualDividendRate": 0.91, "trailingPE": 7.9523816, "trailingAnnualDividendYield": 0.10963856, "epsTrailingTwelveMonths": 1.05, "epsForward": 1.09, "epsCurrentYear": 0.38, "priceEpsCurrentYear": 21.973686, "sharesOutstanding": 126949000, "bookValue": 12.045, "fiftyDayAverage": 8.799, "fiftyDayAverageChange": -0.4489994, "fiftyDayAverageChangePercent": -0.05102846, "twoHundredDayAverage": 9.9585, "twoHundredDayAverageChange": -1.6084995, "twoHundredDayAverageChangePercent": -0.16152026, "marketCap": 1076423552, "forwardPE": 7.6605506, "priceToBook": 0.6932337, "sourceInterval": 15, "exchangeDataDelayedBy": 15, "averageAnalystRating": "1.6 - Buy", "tradeable": false, "cryptoTradeable": false, "symbol": "LD1A.F"}], "error": null}, "summary": {"result": [{"assetProfile": {"address1": "320 Park Avenue", "address2": "15th Floor", "city": "New York", "state": "NY", "zip": "10022", "country": "United States", "phone": "212 715 3170", "website": "https://www.laddercapital.com", "industry": "REIT\u2014Mortgage", "industryDisp": "REIT\u2014Mortgage", "sector": "Real Estate", "longBusinessSummary": "Ladder Capital Corp operates as an internally-managed real estate investment trust in the United States. The company operates through three segments: Loans, Securities, and Real Estate. The Loans segment originates conduit first mortgage loans that are secured by cash-flowing commercial real estate; and originates and invests in balance sheet first mortgage loans secured by commercial real estate properties that are undergoing transition, including lease-up, sell-out, and renovation or repositioning. It also invests in note purchase financings, subordinated debt, mezzanine debt, and other structured finance products related to commercial real estate. The Securities segment invests in commercial mortgage-backed securities and the U.S. Agency Securities. This segment also invests in corporate bonds and equity securities. The Real Estate segment owns and invests in a portfolio of commercial and residential real estate properties, such as leased properties, office buildings, student housing portfolios, hotels, industrial buildings, shopping center, and condominium units. The company qualifies as a real estate investment trust for federal income tax purposes. It generally would not be subject to federal corporate income taxes if it distributes at least 90% of its taxable income to its stockholders. The company was founded in 2008 and is headquartered in New York, New York.", "fullTimeEmployees": 63, "companyOfficers": [{"maxAge": 1, "name": "Mr. Brian Richard Harris", "age": 62, "title": "Founder, CEO & Director", "yearBorn": 1960, "fiscalYear": 2022, "totalPay": {"raw": 7787910, "fmt": "7.79M", "longFmt": "7,787,910"}, "exercisedValue": {"raw": 0, "fmt": null, "longFmt": "0"}, "unexercisedValue": {"raw": 0, "fmt": null, "longFmt": "0"}}, {"maxAge": 1, "name": "Ms. Pamela Lynn McCormack", "age": 52, "title": "Founder, Pres & Director", "yearBorn": 1970, "fiscalYear": 2022, "totalPay": {"raw": 3572410, "fmt": "3.57M", "longFmt": "3,572,410"}, "exercisedValue": {"raw": 0, "fmt": null, "longFmt": "0"}, "unexercisedValue": {"raw": 0, "fmt": null, "longFmt": "0"}}, {"maxAge": 1, "name": "Mr. Robert M. Perelman", "age": 60, "title": "Founder & Head of Asset Management", "yearBorn": 1962, "fiscalYear": 2022, "totalPay": {"raw": 1157006, "fmt": "1.16M", "longFmt": "1,157,006"}, "exercisedValue": {"raw": 0, "fmt": null, "longFmt": "0"}, "unexercisedValue": {"raw": 0, "fmt": null, "longFmt": "0"}}, {"maxAge": 1, "name": "Mr. Paul J. Miceli", "age": 43, "title": "Chief Financial Officer", "yearBorn": 1979, "fiscalYear": 2022, "totalPay": {"raw": 1325162, "fmt": "1.33M", "longFmt": "1,325,162"}, "exercisedValue": {"raw": 0, "fmt": null, "longFmt": "0"}, "unexercisedValue": {"raw": 0, "fmt": null, "longFmt": "0"}}, {"maxAge": 1, "name": "Ms. Kelly Amanda Porcella", "age": 41, "title": "Chief Admin. Officer, Gen. Counsel, Sec. & Head of ESG", "yearBorn": 1981, "fiscalYear": 2022, "totalPay": {"raw": 909004, "fmt": "909k", "longFmt": "909,004"}, "exercisedValue": {"raw": 0, "fmt": null, "longFmt": "0"}, "unexercisedValue": {"raw": 0, "fmt": null, "longFmt": "0"}}, {"maxAge": 1, "name": "Mr. Anthony V. Esposito", "age": 43, "title": "CAO & Principal Accounting Officer", "yearBorn": 1979, "exercisedValue": {"raw": 0, "fmt": null, "longFmt": "0"}, "unexercisedValue": {"raw": 0, "fmt": null, "longFmt": "0"}}, {"maxAge": 1, "name": "Mr. Michael  Cafaro", "title": "Chief Technology Officer", "exercisedValue": {"raw": 0, "fmt": null, "longFmt": "0"}, "unexercisedValue": {"raw": 0, "fmt": null, "longFmt": "0"}}, {"maxAge": 1, "name": "Ms. Michelle  Wallach", "title": "Chief Compliance Officer, Sr. Regulatory Counsel", "exercisedValue": {"raw": 0, "fmt": null, "longFmt": "0"}, "unexercisedValue": {"raw": 0, "fmt": null, "longFmt": "0"}}, {"maxAge": 1, "name": "Mr. Adam  Siper", "title": "Head of Origination", "exercisedValue": {"raw": 0, "fmt": null, "longFmt": "0"}, "unexercisedValue": {"raw": 0, "fmt": null, "longFmt": "0"}}, {"maxAge": 1, "name": "Mr. Michael  Scarola", "title": "Chief Credit Officer", "exercisedValue": {"raw": 0, "fmt": null, "longFmt": "0"}, "unexercisedValue": {"raw": 0, "fmt": null, "longFmt": "0"}}], "auditRisk": 3, "boardRisk": 10, "compensationRisk": 10, "shareHolderRightsRisk": 8, "overallRisk": 10, "governanceEpochDate": 1682899200, "compensationAsOfEpochDate": 1672444800, "maxAge": 86400}}], "error": null}}