{"quote": {"result": [{"language": "en-US", "region": "US", "quoteType": "EQUITY", "typeDisp": "Equity", "quoteSourceName": "Delayed Quote", "triggerable": false, "customPriceAlertConfidence": "LOW", "currency": "EUR", "exchange": "FRA", "shortName": "NU SKIN ENTERPRISES A", "longName": "Nu Skin Enterprises, Inc.", "messageBoardId": "finmb_352094", "exchangeTimezoneName": "Europe/Berlin", "exchangeTimezoneShortName": "CEST", "gmtOffSetMilliseconds": 7200000, "market": "dr_market", "esgPopulated": false, "marketState": "REGULAR", "regularMarketChangePercent": 1.176475, "regularMarketPrice": 34.4, "trailingPE": 24.748203, "trailingAnnualDividendYield": 0.045441177, "epsTrailingTwelveMonths": 1.39, "epsForward": 4.73, "epsCurrentYear": 4.35, "priceEpsCurrentYear": 7.9080467, "sharesOutstanding": 49905300, "bookValue": 17.895, "fiftyDayAverage": 36.5558, "fiftyDayAverageChange": -2.1557999, "fiftyDayAverageChangePercent": -0.05897285, "twoHundredDayAverage": 38.3207, "twoHundredDayAverageChange": -3.9207, "twoHundredDayAverageChangePercent": -0.10231285, "marketCap": 1770210304, "forwardPE": 7.2727275, "priceToBook": 1.9223247, "sourceInterval": 15, "exchangeDataDelayedBy": 15, "averageAnalystRating": "2.4 - Buy", "tradeable": false, "cryptoTradeable": false, "firstTradeDateMilliseconds": 968824800000, "priceHint": 2, "regularMarketChange": 0.40000153, "regularMarketTime": 1683871252, "regularMarketDayHigh": 34.4, "regularMarketDayRange": "34.4 - 34.4", "regularMarketDayLow": 34.4, "regularMarketVolume": 165, "regularMarketPreviousClose": 34.0, "bid": 34.6, "ask": 34.8, "bidSize": 200, "askSize": 200, "fullExchangeName": "Frankfurt", "financialCurrency": "USD", "regularMarketOpen": 34.4, "averageDailyVolume3Month": 5, "averageDailyVolume10Day": 16, "fiftyTwoWeekLowChange": 2.170002, "fiftyTwoWeekLowChangePercent": 0.06732864, "fiftyTwoWeekRange": "32.23 - 46.39", "fiftyTwoWeekHighChange": -11.989998, "fiftyTwoWeekHighChangePercent": -0.25846082, "fiftyTwoWeekLow": 32.23, "fiftyTwoWeekHigh": 46.39, "earningsTimestamp": 1683147600, "earningsTimestampStart": 1690973940, "earningsTimestampEnd": 1691409600, "trailingAnnualDividendRate": 1.545, "symbol": "NUS.F"}], "error": null}, "summary": {"result": [{"assetProfile": {"address1": "75 West Center Street", "city": "Provo", "state": "UT", "zip": "84601", "country": "United States", "phone": "801 345 1000", "fax": "800 487 8000", "website": "https://www.nuskin.com", "industry": "Household & Personal Products", "industryDisp": "Household & Personal Products", "sector": "Consumer Defensive", "longBusinessSummary": "Nu Skin Enterprises, Inc., together with its subsidiaries, develops and distributes various beauty and wellness products worldwide. It offers skin care devices, cosmetics, and other personal care products, including ageLOC LumiSpa and ageLOC LumiSpa iO, ageLOC Body Spa; and nutricentials skin care products. The company also provides wellness products, such as ageLOC Meta, LifePak nutritional supplements, ageLOC TR90 weight management system, and Beauty Focus Collagen+. In addition, it is involved in the research and product development of skin care products and nutritional supplements. The company sells its products under the Nu Skin, Pharmanex, and ageLOC brands through retail stores, website, digital platforms, and independent direct sellers and marketers, as well as a service center. Nu Skin Enterprises, Inc. was founded in 1984 and is headquartered in Provo, Utah.", "fullTimeEmployees": 3800, "companyOfficers": [{"maxAge": 1, "name": "Mr. Steven J. Lund", "age": 69, "title": "Exec. Chairman", "yearBorn": 1953, "fiscalYear": 2022, "totalPay": {"raw": 659212, "fmt": "659.21k", "longFmt": "659,212"}, "exercisedValue": {"raw": 0, "fmt": null, "longFmt": "0"}, "unexercisedValue": {"raw": 0, "fmt": null, "longFmt": "0"}}, {"maxAge": 1, "name": "Mr. Ryan S. Napierski", "age": 48, "title": "Pres, CEO & Director", "yearBorn": 1974, "fiscalYear": 2022, "totalPay": {"raw": 1279397, "fmt": "1.28M", "longFmt": "1,279,397"}, "exercisedValue": {"raw": 886402, "fmt": "886.4k", "longFmt": "886,402"}, "unexercisedValue": {"raw": 2015392, "fmt": "2.02M", "longFmt": "2,015,392"}}, {"maxAge": 1, "name": "Dr. Joseph Y. Chang Ph.D.", "age": 69, "title": "Exec. VP & Chief Scientific Officer", "yearBorn": 1953, "fiscalYear": 2022, "totalPay": {"raw": 907041, "fmt": "907.04k", "longFmt": "907,041"}, "exercisedValue": {"raw": 743363, "fmt": "743.36k", "longFmt": "743,363"}, "unexercisedValue": {"raw": 1570792, "fmt": "1.57M", "longFmt": "1,570,792"}}, {"maxAge": 1, "name": "Mr. Chayce David Clark", "age": 39, "title": "Exec. VP & Gen. Counsel", "yearBorn": 1983, "fiscalYear": 2022, "totalPay": {"raw": 593656, "fmt": "593.66k", "longFmt": "593,656"}, "exercisedValue": {"raw": 0, "fmt": null, "longFmt": "0"}, "unexercisedValue": {"raw": 51407, "fmt": "51.41k", "longFmt": "51,407"}}, {"maxAge": 1, "name": "Ms. Mang Yee  Tang", "age": 51, "title": "Exec. VP and Chief Global Growth & Customer Experience Officer", "yearBorn": 1971, "fiscalYear": 2022, "totalPay": {"raw": 769560, "fmt": "769.56k", "longFmt": "769,560"}, "exercisedValue": {"raw": 0, "fmt": null, "longFmt": "0"}, "unexercisedValue": {"raw": 0, "fmt": null, "longFmt": "0"}}, {"maxAge": 1, "name": "Mr. Blake M. Roney", "age": 63, "title": "Founder", "yearBorn": 1959, "fiscalYear": 2011, "exercisedValue": {"raw": 0, "fmt": null, "longFmt": "0"}, "unexercisedValue": {"raw": 0, "fmt": null, "longFmt": "0"}}, {"maxAge": 1, "name": "Ms. Sandra N. Tillotson", "age": 65, "title": "Founder", "yearBorn": 1957, "fiscalYear": 2012, "exercisedValue": {"raw": 0, "fmt": null, "longFmt": "0"}, "unexercisedValue": {"raw": 0, "fmt": null, "longFmt": "0"}}, {"maxAge": 1, "name": "Mr. James D. Thomas", "age": 43, "title": "Sr. VP, Chief Accounting Officer & Interim CFO", "yearBorn": 1979, "exercisedValue": {"raw": 0, "fmt": null, "longFmt": "0"}, "unexercisedValue": {"raw": 0, "fmt": null, "longFmt": "0"}}, {"maxAge": 1, "name": "Mr. Joe  Sueper", "title": "Sr. VP & CTO", "exercisedValue": {"raw": 0, "fmt": null, "longFmt": "0"}, "unexercisedValue": {"raw": 0, "fmt": null, "longFmt": "0"}}, {"maxAge": 1, "name": "Mr. Mark L. Adams", "age": 70, "title": "Chief Information Officer", "yearBorn": 1952, "exercisedValue": {"raw": 0, "fmt": null, "longFmt": "0"}, "unexercisedValue": {"raw": 0, "fmt": null, "longFmt": "0"}}], "auditRisk": 4, "boardRisk": 3, "compensationRisk": 2, "shareHolderRightsRisk": 4, "overallRisk": 3, "governanceEpochDate": 1682899200, "compensationAsOfEpochDate": 1672444800, "maxAge": 86400}}], "error": null}}