{"quote": {"result": [{"language": "en-US", "region": "US", "quoteType": "EQUITY", "typeDisp": "Equity", "quoteSourceName": "Delayed Quote", "triggerable": false, "customPriceAlertConfidence": "LOW", "currency": "EUR", "regularMarketChangePercent": -7.863606, "regularMarketPrice": 6.62, "earningsTimestamp": 1683147600, "earningsTimestampStart": 1690887540, "earningsTimestampEnd": 1691409600, "trailingAnnualDividendRate": 0.0, "trailingAnnualDividendYield": 0.0, "epsTrailingTwelveMonths": -0.03, "sharesOutstanding": 207988992, "bookValue": 7.054, "fiftyDayAverage": 7.15186, "fiftyDayAverageChange": -0.53186035, "fiftyDayAverageChangePercent": -0.07436672, "twoHundredDayAverage": 9.46754, "twoHundredDayAverageChange": -2.84754, "twoHundredDayAverageChangePercent": -0.30076873, "marketCap": 1643812224, "priceToBook": 0.9384746, "sourceInterval": 15, "exchangeDataDelayedBy": 15, "tradeable": false, "cryptoTradeable": false, "firstTradeDateMilliseconds": 1198825200000, "priceHint": 2, "marketState": "REGULAR", "exchange": "FRA", "shortName": "GREEN THUMB INDS", "longName": "Green Thumb Industries Inc.", "messageBoardId": "finmb_560549330", "exchangeTimezoneName": "Europe/Berlin", "exchangeTimezoneShortName": "CEST", "gmtOffSetMilliseconds": 7200000, "market": "dr_market", "esgPopulated": false, "regularMarketChange": -0.56500006, "regularMarketTime": 1683892036, "regularMarketDayHigh": 6.625, "regularMarketDayRange": "6.605 - 6.625", "regularMarketDayLow": 6.605, "regularMarketVolume": 25, "regularMarketPreviousClose": 7.185, "bid": 6.625, "ask": 6.785, "fullExchangeName": "Frankfurt", "financialCurrency": "USD", "regularMarketOpen": 6.605, "averageDailyVolume3Month": 140, "averageDailyVolume10Day": 161, "fiftyTwoWeekLowChange": 0.60999966, "fiftyTwoWeekLowChangePercent": 0.10149744, "fiftyTwoWeekRange": "6.01 - 15.025", "fiftyTwoWeekHighChange": -8.405, "fiftyTwoWeekHighChangePercent": -0.559401, "fiftyTwoWeekLow": 6.01, "fiftyTwoWeekHigh": 15.025, "symbol": "R9U2.F"}], "error": null}, "summary": {"result": [{"assetProfile": {"address1": "325 West Huron Street", "city": "Chicago", "state": "IL", "zip": "60654", "country": "United States", "phone": "312 471 6720", "website": "https://www.gtigrows.com", "industry": "Drug Manufacturers\u2014Specialty & Generic", "industryDisp": "Drug Manufacturers\u2014Specialty & Generic", "sector": "Healthcare", "longBusinessSummary": "Green Thumb Industries Inc. engages in the manufacture, distribution, and sale of various cannabis products for medical and adult-use in the United States. The company offers cannabis flower; processed and packaged products, including pre-rolls, concentrates, vapes, capsules, tinctures, edibles, topicals, and other cannabis-related products under the &Shine, Beboe, Dogwalkers, Doctor Solomon's, Good Green, incredibles, and RHYTHM brands. It distributes its products primarily to third-party retail stores, as well as sells finished products directly to consumers in its own retail stores. Green Thumb Industries Inc. was founded in 2014 and is headquartered in Chicago, Illinois.", "fullTimeEmployees": 3880, "companyOfficers": [{"maxAge": 1, "name": "Mr. Benjamin  Kovler", "age": 43, "title": "Founder, Chairman & CEO", "yearBorn": 1979, "fiscalYear": 2021, "totalPay": {"raw": 1214256, "fmt": "1.21M", "longFmt": "1,214,256"}, "exercisedValue": {"raw": 0, "fmt": null, "longFmt": "0"}, "unexercisedValue": {"raw": 3492516, "fmt": "3.49M", "longFmt": "3,492,516"}}, {"maxAge": 1, "name": "Mr. Anthony  Georgiadis", "age": 44, "title": "Pres & Director", "yearBorn": 1978, "fiscalYear": 2021, "totalPay": {"raw": 1044494, "fmt": "1.04M", "longFmt": "1,044,494"}, "exercisedValue": {"raw": 0, "fmt": null, "longFmt": "0"}, "unexercisedValue": {"raw": 3492516, "fmt": "3.49M", "longFmt": "3,492,516"}}, {"maxAge": 1, "name": "Mr. Mathew  Faulkner", "age": 48, "title": "Chief Financial Officer", "yearBorn": 1974, "exercisedValue": {"raw": 0, "fmt": null, "longFmt": "0"}, "unexercisedValue": {"raw": 0, "fmt": null, "longFmt": "0"}}, {"maxAge": 1, "name": "Mr. Swadheen  Sehgal", "title": "Chief Information Officer", "exercisedValue": {"raw": 0, "fmt": null, "longFmt": "0"}, "unexercisedValue": {"raw": 0, "fmt": null, "longFmt": "0"}}, {"maxAge": 1, "name": "Ms. Rachel  Albert", "title": "Chief Admin. Officer", "exercisedValue": {"raw": 0, "fmt": null, "longFmt": "0"}, "unexercisedValue": {"raw": 0, "fmt": null, "longFmt": "0"}}, {"maxAge": 1, "name": "Mr. Andrew Laurence Grossman", "age": 48, "title": "EVP of Capital Markets & Investor Relations", "yearBorn": 1974, "fiscalYear": 2018, "exercisedValue": {"raw": 0, "fmt": null, "longFmt": "0"}, "unexercisedValue": {"raw": 0, "fmt": null, "longFmt": "0"}}, {"maxAge": 1, "name": "Mr. Bret  Kravitz", "age": 41, "title": "Gen. Counsel & Sec.", "yearBorn": 1981, "exercisedValue": {"raw": 0, "fmt": null, "longFmt": "0"}, "unexercisedValue": {"raw": 0, "fmt": null, "longFmt": "0"}}, {"maxAge": 1, "name": "Ms. Linda  Marsicano", "age": 54, "title": "VP of Communications", "yearBorn": 1968, "exercisedValue": {"raw": 0, "fmt": null, "longFmt": "0"}, "unexercisedValue": {"raw": 0, "fmt": null, "longFmt": "0"}}, {"maxAge": 1, "name": "Mr. Daniel  Shaker", "age": 51, "title": "Sr. VP of National Sales", "yearBorn": 1971, "exercisedValue": {"raw": 0, "fmt": null, "longFmt": "0"}, "unexercisedValue": {"raw": 0, "fmt": null, "longFmt": "0"}}, {"maxAge": 1, "name": "Ms. Kate  Denton", "title": "Sr. VP of Marketing", "exercisedValue": {"raw": 0, "fmt": null, "longFmt": "0"}, "unexercisedValue": {"raw": 0, "fmt": null, "longFmt": "0"}}], "compensationAsOfEpochDate": 1640908800, "maxAge": 86400}}], "error": null}}