{"quote": {"result": [{"language": "en-US", "region": "US", "quoteType": "EQUITY", "typeDisp": "Equity", "quoteSourceName": "Delayed Quote", "triggerable": false, "customPriceAlertConfidence": "LOW", "currency": "IDR", "regularMarketChangePercent": 0.0, "regularMarketPrice": 62.0, "trailingAnnualDividendRate": 0.0, "trailingAnnualDividendYield": 0.0, "epsTrailingTwelveMonths": -2.02, "sharesOutstanding": 15537600512, "bookValue": 10.625, "fiftyDayAverage": 63.68, "fiftyDayAverageChange": -1.6800003, "fiftyDayAverageChangePercent": -0.026381914, "twoHundredDayAverage": 71.125, "twoHundredDayAverageChange": -9.125, "twoHundredDayAverageChangePercent": -0.12829526, "marketCap": 963331227648, "priceToBook": 5.8352942, "sourceInterval": 10, "exchangeDataDelayedBy": 10, "prevName": "PT Wilton Makmur indonesia Tbk", "nameChangeDate": "2023-05-12", "tradeable": false, "cryptoTradeable": false, "firstTradeDateMilliseconds": 1089943200000, "priceHint": 2, "marketState": "CLOSED", "exchange": "JKT", "shortName": "Wilton Makmur Indonesia Tbk.", "longName": "PT Wilton Makmur indonesia Tbk.", "messageBoardId": "finmb_20405362", "exchangeTimezoneName": "Asia/Jakarta", "exchangeTimezoneShortName": "WIB", "gmtOffSetMilliseconds": 25200000, "market": "id_market", "esgPopulated": false, "regularMarketChange": 0.0, "regularMarketTime": 1683882003, "regularMarketDayHigh": 63.0, "regularMarketDayRange": "61.0 - 63.0", "regularMarketDayLow": 61.0, "regularMarketVolume": 6962900, "regularMarketPreviousClose": 62.0, "bid": 61.0, "ask": 62.0, "bidSize": 0, "askSize": 0, "fullExchangeName": "Jakarta", "financialCurrency": "IDR", "regularMarketOpen": 62.0, "averageDailyVolume3Month": 10027254, "averageDailyVolume10Day": 11169710, "fiftyTwoWeekLowChange": 7.0, "fiftyTwoWeekLowChangePercent": 0.12727273, "fiftyTwoWeekRange": "55.0 - 95.0", "fiftyTwoWeekHighChange": -33.0, "fiftyTwoWeekHighChangePercent": -0.34736842, "fiftyTwoWeekLow": 55.0, "fiftyTwoWeekHigh": 95.0, "symbol": "SQMI.JK"}], "error": null}, "summary": {"result": [{"assetProfile": {"address1": "Komplek Harco Mangga Dua", "address2": "(Agung Sedayu) Blok C number 5a Jalan Mangga Dua Raya", "city": "Jakarta", "zip": "10730", "country": "Indonesia", "phone": "62 21 612 5588", "fax": "62 21 612 5583", "website": "https://www.wilton.id", "industry": "Gold", "industryDisp": "Gold", "sector": "Basic Materials", "longBusinessSummary": "PT Wilton Makmur indonesia Tbk., together with its subsidiaries, engages in the exploration and mining of gold in Indonesia. The company holds interest in the Ciemas Gold Project that covers a total area of 3,078.5 hectares located in West Java, Indonesia. It is also involved in the trading of various natural resources, such as zirconium, lead, and coal. The company was formerly known as PT Renuka Coalindo Tbk and changed its name to PT Wilton Makmur indonesia Tbk. in October 2019. The company was founded in 2000 and is headquartered in Jakarta, Indonesia. PT Wilton Makmur indonesia Tbk. is a subsidiary of Wilton Resources Holding Pte. Ltd.", "companyOfficers": [{"maxAge": 1, "name": "Oktavia Budi Raharjo", "title": "Pres Director", "exercisedValue": {"raw": 0, "fmt": null, "longFmt": "0"}, "unexercisedValue": {"raw": 0, "fmt": null, "longFmt": "0"}}], "maxAge": 86400}}], "error": null}}